odoo10_addon_web_shortcut-10.0.1.0.1-py2.7-nspkg.pth
odoo/addons/web_shortcut/LICENSE
odoo/addons/web_shortcut/README.rst
odoo/addons/web_shortcut/__init__.py
odoo/addons/web_shortcut/__manifest__.py
odoo/addons/web_shortcut/i18n/ar.po
odoo/addons/web_shortcut/i18n/bs.po
odoo/addons/web_shortcut/i18n/cs.po
odoo/addons/web_shortcut/i18n/da.po
odoo/addons/web_shortcut/i18n/de.po
odoo/addons/web_shortcut/i18n/el.po
odoo/addons/web_shortcut/i18n/en_GB.po
odoo/addons/web_shortcut/i18n/es.po
odoo/addons/web_shortcut/i18n/fi.po
odoo/addons/web_shortcut/i18n/fr.po
odoo/addons/web_shortcut/i18n/gl.po
odoo/addons/web_shortcut/i18n/hr.po
odoo/addons/web_shortcut/i18n/hu.po
odoo/addons/web_shortcut/i18n/it.po
odoo/addons/web_shortcut/i18n/lt.po
odoo/addons/web_shortcut/i18n/mk.po
odoo/addons/web_shortcut/i18n/mn.po
odoo/addons/web_shortcut/i18n/nl.po
odoo/addons/web_shortcut/i18n/nl_NL.po
odoo/addons/web_shortcut/i18n/pl.po
odoo/addons/web_shortcut/i18n/pt.po
odoo/addons/web_shortcut/i18n/pt_BR.po
odoo/addons/web_shortcut/i18n/ro.po
odoo/addons/web_shortcut/i18n/ru.po
odoo/addons/web_shortcut/i18n/sl.po
odoo/addons/web_shortcut/i18n/sv.po
odoo/addons/web_shortcut/i18n/th.po
odoo/addons/web_shortcut/i18n/tr.po
odoo/addons/web_shortcut/i18n/vi.po
odoo/addons/web_shortcut/i18n/web_shortcut.pot
odoo/addons/web_shortcut/i18n/zh_CN.po
odoo/addons/web_shortcut/i18n/zh_TW.po
odoo/addons/web_shortcut/models/__init__.py
odoo/addons/web_shortcut/models/ir_ui_menu.py
odoo/addons/web_shortcut/models/web_shortcut.py
odoo/addons/web_shortcut/security/ir.model.access.csv
odoo/addons/web_shortcut/static/description/icon.png
odoo/addons/web_shortcut/static/src/css/web_shortcut.css
odoo/addons/web_shortcut/static/src/js/web_shortcut.js
odoo/addons/web_shortcut/static/src/xml/web_shortcut.xml
odoo/addons/web_shortcut/templates/assets.xml
odoo/addons/web_shortcut/tests/__init__.py
odoo/addons/web_shortcut/tests/test_web_shortcut.py
odoo10_addon_web_shortcut-10.0.1.0.1.dist-info/DESCRIPTION.rst
odoo10_addon_web_shortcut-10.0.1.0.1.dist-info/METADATA
odoo10_addon_web_shortcut-10.0.1.0.1.dist-info/RECORD
odoo10_addon_web_shortcut-10.0.1.0.1.dist-info/WHEEL
odoo10_addon_web_shortcut-10.0.1.0.1.dist-info/metadata.json
odoo10_addon_web_shortcut-10.0.1.0.1.dist-info/namespace_packages.txt
odoo10_addon_web_shortcut-10.0.1.0.1.dist-info/top_level.txt
